[
  {
    "title": "Pop-Up Makers Market at Second Shift Coworking",
    "date": "2024-11-23T18:00:00Z",
    "description": "Come support local creatives at our makers market!",
    "link": "https://plan.getpie.app/plans/c825ec00-8d60-11ef-9607-49c1d718b127?inviter=c85a6980-8d60-11ef-9607-49c1d718b127",
    "month": "November",
    "id": "makers-market-november"
  },
  {
    "title": "Bring-Your-Own-Craft at Glessner House",
    "date": "2024-11-24T20:00:00Z",
    "description": "Come craft with us at the historic Glessner House!",
    "link": "https://plan.getpie.app/plans/4211a8c0-8c84-11ef-9607-49c1d718b127?inviter=423cd770-8c84-11ef-9607-49c1d718b127",
    "month": "November",
    "id": "glessner-house-november"
  },
  {
    "title": "Coffee & Crafts",
    "date": "2024-12-21T17:00:00Z",
    "description": "Bring a craft (spoiler: anything is a craft!), meet us at Pilot Project, and enjoy their full espresso bar while you create.",
    "link": "https://plan.getpie.app/plans/2042c580-a91c-11ef-a00d-91453a826ac2?inviter=206f53c0-a91c-11ef-a00d-91453a826ac2",
    "month": "December",
    "id": "pilot-project-december"
  },
  {
    "title": "Bring-Your-Own-Craft at Pinot's Palette",
    "date": "2024-12-10T00:00:00Z",
    "description": "Join us at Pinot's Palette for a bring-your-own-craft meetup! Drinks will be available from their bar while you create (NA options available), and Chiya Chai is right next door for a delicious dinner option to bring in with you.",
    "link": "https://plan.getpie.app/plans/b9f0f710-a91c-11ef-a00d-91453a826ac2?inviter=ba24ff60-a91c-11ef-a00d-91453a826ac2",
    "month": "December",
    "id": "pinots-palette-december"
  }
]
